_dlib_pybind11.cp310-win_amd64.pyd
dlib/__init__.py
dlib_binary-19.24.1.dist-info/METADATA
dlib_binary-19.24.1.dist-info/WHEEL
dlib_binary-19.24.1.dist-info/top_level.txt
dlib_binary-19.24.1.dist-info/RECORD
